maxgradient-0.3.1.dist-info/METADATA
maxgradient-0.3.1.dist-info/WHEEL
maxgradient-0.3.1.dist-info/entry_points.txt
maxgradient-0.3.1.dist-info/licenses/LICENSE
maxgradient/.DS_Store
maxgradient/.mypy_cache/.gitignore
maxgradient/.mypy_cache/3.11/@plugins_snapshot.json
maxgradient/.mypy_cache/3.11/IPython/__init__.data.json
maxgradient/.mypy_cache/3.11/IPython/__init__.meta.json
maxgradient/.mypy_cache/3.11/IPython/core/__init__.data.json
maxgradient/.mypy_cache/3.11/IPython/core/__init__.meta.json
maxgradient/.mypy_cache/3.11/IPython/core/alias.data.json
maxgradient/.mypy_cache/3.11/IPython/core/alias.meta.json
maxgradient/.mypy_cache/3.11/IPython/core/application.data.json
maxgradient/.mypy_cache/3.11/IPython/core/application.meta.json
maxgradient/.mypy_cache/3.11/IPython/core/async_helpers.data.json
maxgradient/.mypy_cache/3.11/IPython/core/async_helpers.meta.json
maxgradient/.mypy_cache/3.11/IPython/core/autocall.data.json
maxgradient/.mypy_cache/3.11/IPython/core/autocall.meta.json
maxgradient/.mypy_cache/3.11/IPython/core/builtin_trap.data.json
maxgradient/.mypy_cache/3.11/IPython/core/builtin_trap.meta.json
maxgradient/.mypy_cache/3.11/IPython/core/compilerop.data.json
maxgradient/.mypy_cache/3.11/IPython/core/compilerop.meta.json
maxgradient/.mypy_cache/3.11/IPython/core/completer.data.json
maxgradient/.mypy_cache/3.11/IPython/core/completer.meta.json
maxgradient/.mypy_cache/3.11/IPython/core/completerlib.data.json
maxgradient/.mypy_cache/3.11/IPython/core/completerlib.meta.json
maxgradient/.mypy_cache/3.11/IPython/core/crashhandler.data.json
maxgradient/.mypy_cache/3.11/IPython/core/crashhandler.meta.json
maxgradient/.mypy_cache/3.11/IPython/core/debugger.data.json
maxgradient/.mypy_cache/3.11/IPython/core/debugger.meta.json
maxgradient/.mypy_cache/3.11/IPython/core/display.data.json
maxgradient/.mypy_cache/3.11/IPython/core/display.meta.json
maxgradient/.mypy_cache/3.11/IPython/core/display_functions.data.json
maxgradient/.mypy_cache/3.11/IPython/core/display_functions.meta.json
maxgradient/.mypy_cache/3.11/IPython/core/display_trap.data.json
maxgradient/.mypy_cache/3.11/IPython/core/display_trap.meta.json
maxgradient-0.3.1.dist-info/RECORD
