Metadata-Version: 2.1
Name: maxgradient
Version: 0.3.1
Summary: MaxGradient automates the printing gradient colored text to the console.
Author-Email: Max Ludden <dev@maxludden.com>
License: MIT
Requires-Python: >=3.10
Requires-Dist: lorem-text>=2.1
Requires-Dist: loguru>=0.7.2
Requires-Dist: numpy>=1.25.2
Requires-Dist: pendulum>=2.1.2
Requires-Dist: python-dotenv>=1.0.0
Requires-Dist: pydantic>=2.5.0
Requires-Dist: rich>=13.5.3
Requires-Dist: typer>=0.9.0
Requires-Dist: pydantic-extra-types>=2.4.1
Requires-Dist: pydantic-settings>=2.1.0
Requires-Dist: snoop>=0.4.3
Requires-Dist: mkdocstrings>=0.24.0
Requires-Dist: mkdocs>=1.5.2; extra == "dev"
Requires-Dist: mkdocs-material>=9.4.7; extra == "dev"
Requires-Dist: mkdocstrings[python]>=0.18; extra == "dev"
Requires-Dist: typer[all]>=0.9.0; extra == "cli"
Provides-Extra: dev
Provides-Extra: cli
